{
  "feature_names": [
    "close_denoised",
    "close_noise",
    "noise_ratio",
    "ema_9",
    "ema_9_dn",
    "ema_21",
    "ema_21_dn",
    "ema_50",
    "ema_50_dn",
    "ema_200",
    "ema_200_dn",
    "ema_9_21_cross",
    "ema_9_50_cross",
    "ema_21_50_cross",
    "price_vs_ema50",
    "price_vs_ema200",
    "macd",
    "macd_signal",
    "macd_histogram",
    "macd_hist_slope",
    "adx",
    "adx_pos",
    "adx_neg",
    "adx_diff",
    "ichi_a",
    "ichi_b",
    "ichi_diff",
    "sma_10",
    "sma_30",
    "sma_10_30_cross",
    "rsi",
    "rsi_7",
    "rsi_21",
    "rsi_slope",
    "stoch_k",
    "stoch_d",
    "stoch_diff",
    "williams_r",
    "roc_3",
    "roc_5",
    "roc_10",
    "roc_20",
    "awesome_osc",
    "cci",
    "bb_upper",
    "bb_lower",
    "bb_width",
    "bb_pct",
    "atr",
    "atr_pct",
    "atr_ratio",
    "kc_upper",
    "kc_lower",
    "kc_width",
    "obv",
    "obv_change",
    "obv_slope",
    "vwap",
    "price_vs_vwap",
    "volume_ratio",
    "volume_ratio_5",
    "volume_spike",
    "mfi",
    "force_index",
    "body_size",
    "upper_shadow",
    "lower_shadow",
    "is_bullish_candle",
    "bullish_streak",
    "is_doji",
    "return_1d",
    "return_3d",
    "return_5d",
    "return_10d",
    "return_20d",
    "return_60d",
    "high_low_range",
    "close_open_range",
    "volatility_5",
    "volatility_10",
    "volatility_20",
    "volatility_ratio",
    "regime_trend",
    "regime_momentum",
    "regime_volatility",
    "market_phase",
    "near_high_20",
    "near_low_20",
    "range_position",
    "gap_pct",
    "gap_fill",
    "skewness_20",
    "kurtosis_20",
    "zscore_20",
    "day_sin",
    "day_cos",
    "month_sin",
    "month_cos"
  ],
  "selected_features": [
    "close_denoised",
    "close_noise",
    "noise_ratio",
    "ema_9",
    "ema_21",
    "ema_21_dn",
    "ema_50",
    "ema_200",
    "ema_9_21_cross",
    "ema_21_50_cross",
    "price_vs_ema50",
    "price_vs_ema200",
    "macd",
    "macd_signal",
    "macd_histogram",
    "macd_hist_slope",
    "adx",
    "adx_pos",
    "adx_neg",
    "adx_diff",
    "ichi_a",
    "ichi_b",
    "ichi_diff",
    "sma_10",
    "sma_30",
    "sma_10_30_cross",
    "rsi",
    "rsi_7",
    "rsi_21",
    "rsi_slope",
    "stoch_k",
    "stoch_d",
    "stoch_diff",
    "roc_3",
    "roc_5",
    "roc_10",
    "roc_20",
    "awesome_osc",
    "cci",
    "bb_upper",
    "bb_lower",
    "bb_width",
    "bb_pct",
    "atr",
    "atr_pct",
    "atr_ratio",
    "kc_upper",
    "kc_width",
    "obv",
    "obv_change",
    "obv_slope",
    "price_vs_vwap",
    "volume_ratio",
    "volume_ratio_5",
    "mfi",
    "force_index",
    "body_size",
    "upper_shadow",
    "lower_shadow",
    "bullish_streak",
    "return_1d",
    "return_60d",
    "high_low_range",
    "close_open_range",
    "volatility_5",
    "volatility_10",
    "volatility_20",
    "volatility_ratio",
    "market_phase",
    "near_high_20",
    "near_low_20",
    "range_position",
    "gap_pct",
    "gap_fill",
    "skewness_20",
    "kurtosis_20",
    "day_sin",
    "day_cos",
    "month_sin",
    "month_cos"
  ],
  "metrics": {
    "lstm": {
      "accuracy": 0.5351,
      "f1": 0.6885,
      "mae": 1.1195
    },
    "xgboost": {
      "accuracy": 0.7302,
      "f1": 0.7475,
      "mae": 0.8742
    },
    "ensemble": {
      "accuracy": 0.7256,
      "f1": 0.7472,
      "mae": 0.8751
    },
    "ensemble_weights": {
      "lstm": 0.1,
      "xgb": 0.9
    },
    "n_features_selected": 80,
    "n_features_total": 98
  },
  "ensemble_weights": {
    "lstm": 0.1,
    "xgb": 0.9
  },
  "feature_importance": {
    "close_denoised": 0.011274910531938076,
    "close_noise": 0.054029885679483414,
    "noise_ratio": 0.023099910467863083,
    "ema_9": 0.010442335158586502,
    "ema_21": 0.011801457963883877,
    "ema_21_dn": 0.011942821554839611,
    "ema_50": 0.011274940334260464,
    "ema_200": 0.01101352646946907,
    "ema_9_21_cross": 0.010709353722631931,
    "ema_21_50_cross": 0.011486666277050972,
    "price_vs_ema50": 0.012498446740210056,
    "price_vs_ema200": 0.010665851645171642,
    "macd": 0.01133567001670599,
    "macd_signal": 0.010443967767059803,
    "macd_histogram": 0.009535747580230236,
    "macd_hist_slope": 0.012537054717540741,
    "adx": 0.010022493079304695,
    "adx_pos": 0.010463905520737171,
    "adx_neg": 0.011005431413650513,
    "adx_diff": 0.012019569985568523,
    "ichi_a": 0.011841032654047012,
    "ichi_b": 0.012114234268665314,
    "ichi_diff": 0.009645452722907066,
    "sma_10": 0.01102688442915678,
    "sma_30": 0.012261948548257351,
    "sma_10_30_cross": 0.010507115162909031,
    "rsi": 0.010483925230801105,
    "rsi_7": 0.019779155030846596,
    "rsi_21": 0.01206723041832447,
    "rsi_slope": 0.017394408583641052,
    "stoch_k": 0.013373813591897488,
    "stoch_d": 0.011292725801467896,
    "stoch_diff": 0.015530752949416637,
    "roc_3": 0.03144940361380577,
    "roc_5": 0.01650867611169815,
    "roc_10": 0.011062944307923317,
    "roc_20": 0.01478462852537632,
    "awesome_osc": 0.013224092312157154,
    "cci": 0.012377876788377762,
    "bb_upper": 0.012149629183113575,
    "bb_lower": 0.012303500436246395,
    "bb_width": 0.010865536518394947,
    "bb_pct": 0.014693837612867355,
    "atr": 0.010383978486061096,
    "atr_pct": 0.010198308154940605,
    "atr_ratio": 0.010582289658486843,
    "kc_upper": 0.014146544970571995,
    "kc_width": 0.011437159962952137,
    "obv": 0.009712300263345242,
    "obv_change": 0.00949125736951828,
    "obv_slope": 0.009739713743329048,
    "price_vs_vwap": 0.014905424788594246,
    "volume_ratio": 0.010313941165804863,
    "volume_ratio_5": 0.00982169434428215,
    "mfi": 0.010243000462651253,
    "force_index": 0.010753076523542404,
    "body_size": 0.011275919154286385,
    "upper_shadow": 0.009677494876086712,
    "lower_shadow": 0.010579215362668037,
    "bullish_streak": 0.01029818132519722,
    "return_1d": 0.01640644669532776,
    "return_60d": 0.010519744828343391,
    "high_low_range": 0.011895411647856236,
    "close_open_range": 0.012991675175726414,
    "volatility_5": 0.011199044063687325,
    "volatility_10": 0.010178889147937298,
    "volatility_20": 0.010738873854279518,
    "volatility_ratio": 0.010729419998824596,
    "market_phase": 0.012580985203385353,
    "near_high_20": 0.010218320414423943,
    "near_low_20": 0.01211322471499443,
    "range_position": 0.011482658796012402,
    "gap_pct": 0.010520609095692635,
    "gap_fill": 0.010381996631622314,
    "skewness_20": 0.01058400608599186,
    "kurtosis_20": 0.00973106361925602,
    "day_sin": 0.008261911571025848,
    "day_cos": 0.009660700336098671,
    "month_sin": 0.010678350925445557,
    "month_cos": 0.011224433779716492
  }
}